depth_to_mesh/__init__.py
depth_to_mesh/__main__.py
depth_to_mesh-0.1.6.dist-info/LICENSE.md
depth_to_mesh-0.1.6.dist-info/METADATA
depth_to_mesh-0.1.6.dist-info/WHEEL
depth_to_mesh-0.1.6.dist-info/top_level.txt
depth_to_mesh-0.1.6.dist-info/RECORD
