Metadata-Version: 2.1
Name: depth-to-mesh
Version: 0.1.6
Summary: Converts depth maps into triangle meshes
Home-page: https://github.com/hesom/depth_to_mesh
Author: Hendrik Sommerhoff
Author-email: sommerhoff.hendrik@gmail.com
License: MIT
License-File: LICENSE.md
Requires-Dist: open3d<0.19,>=0.18
Requires-Dist: numpy
Requires-Dist: scikit-image
Requires-Dist: tqdm
